{
  "teams": [
    {
      "id": 1,
      "name": "名古屋大学",
      "leg_ranks": [
        9,
        9,
        4,
        1,
        1,
        1,
        1,
        1,
        1,
        1
      ]
    },
    {
      "id": 2,
      "name": "三重大学",
      "leg_ranks": [
        16,
        16,
        15,
        15,
        13,
        11,
        11,
        11,
        10,
        9
      ]
    },
    {
      "id": 3,
      "name": "福岡大学",
      "leg_ranks": [
        4,
        4,
        8,
        5,
        7,
        9,
        7,
        8,
        9,
        8
      ]
    },
    {
      "id": 4,
      "name": "上武大学",
      "leg_ranks": [
        3,
        5,
        6,
        7,
        2,
        2,
        2,
        2,
        2,
        2
      ]
    },
    {
      "id": 5,
      "name": "関西大学",
      "leg_ranks": [
        7,
        10,
        9,
        9,
        6,
        6,
        3,
        3,
        3,
        3
      ]
    },
    {
      "id": 6,
      "name": "熊本学園大学",
      "leg_ranks": [
        10,
        12,
        11,
        10,
        12,
        13,
        12,
        12,
        12,
        12
      ]
    },
    {
      "id": 7,
      "name": "鹿児島大学",
      "leg_ranks": [
        17,
        17,
        17,
        17,
        17,
        17,
        15,
        14,
        13,
        null
      ]
    },
    {
      "id": 8,
      "name": "広島経済大学",
      "leg_ranks": [
        12,
        12,
        5,
        6,
        4,
        3,
        4,
        5,
        6,
        6
      ]
    },
    {
      "id": 9,
      "name": "学連選抜",
      "leg_ranks": [
        2,
        11,
        12,
        11,
        9,
        10,
        5,
        4,
        5,
        7
      ]
    },
    {
      "id": 10,
      "name": "山梨学院大学",
      "leg_ranks": [
        11,
        14,
        14,
        14,
        11,
        7,
        8,
        7,
        6,
        4
      ]
    },
    {
      "id": 11,
      "name": "鳥取大学",
      "leg_ranks": [
        8,
        3,
        3,
        2,
        4,
        5,
        9,
        9,
        8,
        10
      ]
    },
    {
      "id": 12,
      "name": "四国大学",
      "leg_ranks": [
        15,
        15,
        16,
        16,
        16,
        16,
        17,
        13,
        14,
        null
      ]
    },
    {
      "id": 13,
      "name": "日本大学",
      "leg_ranks": [
        14,
        7,
        7,
        11,
        10,
        8,
        10,
        10,
        11,
        11
      ]
    },
    {
      "id": 14,
      "name": "立命館大学",
      "leg_ranks": [
        4,
        2,
        1,
        4,
        3,
        4,
        6,
        4,
        4,
        5
      ]
    },
    {
      "id": 15,
      "name": "福島大学",
      "leg_ranks": [
        1,
        1,
        2,
        3,
        8,
        11,
        14,
        16,
        17,
        null
      ]
    },
    {
      "id": 16,
      "name": "琉球大学",
      "leg_ranks": [
        18,
        18,
        18,
        18,
        18,
        18,
        18,
        18,
        18,
        null
      ]
    },
    {
      "id": 17,
      "name": "金沢大学",
      "leg_ranks": [
        13,
        8,
        13,
        13,
        14,
        14,
        13,
        15,
        15,
        null
      ]
    },
    {
      "id": 18,
      "name": "東北大学",
      "leg_ranks": [
        6,
        6,
        10,
        8,
        15,
        15,
        16,
        16,
        16,
        null
      ]
    }
  ]
}