[
  {
    "timestamp": "2025-08-14T05:39:00",
    "posted_name": "■○○(立命館大学監督）",
    "official_name": "○○（立命館大学監督）",
    "tripcode": "◆x59qz04G1I",
    "content_html": "<div class=\"post-content\"> （関西大学） <br/> 昨日の郡家は猛暑日で日順位１位でした <br/> おととい昨日と日順位１位と、２日連続の日順位１位獲得です <br/> 今日の郡家の走りはどうなるでしょうか？ <br/> <br/> ところで、９区１０区の戦い方に関して、大変頭が痛いです <br/> どうしたものか、判断が難しいです <br/> 関西大学は補欠をまだ使っておりません <br/> 補欠カードを切るべきか、切らないべきか・・・ <br/> というより、補欠カードを使わずレース終了の可能性もあるかもしれません <br/> <br/> やはり序盤１区２区の戦い方が大間違いでした <br/> 立命館大学での２０２３年の１区２区の裏目がトラウマになって、過度に慎重になり、その回避法が間違っておりました <br/> 「序盤で失敗しても、その後で少しずつでも取り返せばいい」と開き直ればよかった・・・ <br/> ものすごく後悔しております（泣） </div>"
  },
  {
    "timestamp": "2025-08-14T05:25:21",
    "posted_name": "■○○(立命館大学監督）",
    "official_name": "○○（立命館大学監督）",
    "tripcode": "◆x59qz04G1I",
    "content_html": "<div class=\"post-content\"> （立命館大学） <br/> どうも北風基調が強まったようで、京都の予想最高気温が天気予報更新のたびに下がっております <br/> こういう時に京都出走というのはレース展開を考えると本来「助かる」のですが・・・ <br/> もしかしたら、「京都でも高速レースにはついていけない」というパターンかもしれません <br/> <br/> 結果論ですが、６区７区の「悪路は琵琶湖沿岸でしのぐ」の失敗が痛いということになりそうです </div>"
  },
  {
    "timestamp": "2025-08-14T00:36:58",
    "posted_name": "■名古屋大学監督(ロマン派)",
    "official_name": "名古屋大学監督（ロマン派)",
    "tripcode": "◆Ai4OO8X72O3b",
    "content_html": "<div class=\"post-content\"><span class=\"AA\"> ８月１３日　２２日目　 結果 <br/> 　 　 　 　 　 　 　　 　 　　本日　.　.　.　.　.総合 <br/> 　大学名　.　.　走者　.　距離 . 順位　.　距離　. 　順位　. 次走者　.　被交代選手　 <br/> 名古屋大　.　8大府＿　34.4　.　05　.　795.0　.　01(01)　9揖斐川 <br/> 上武大学　.　8前橋＿　33.1　.　11　.　785.1　.　02(02)　9館林 <br/> 関西大学　.　8郡家＿　35.3　.　01　.　783.1　.　03(03)　9西脇 <br/> 学連選抜　.　8飯塚＿　34.6　.　03　.　771.9　.　04(05)　9恵那 <br/> 広島経済　.　8引田＿　33.4　.　08　.　771.6　.　05(04)　9滝宮 <br/> 立命館大　.　8京都＿　33.9　.　06　.　770.1　.　06(06)　9園部 <br/> 福岡大学　.　7口之津　33.8　.　07　.　768.2　.　07(07)　8大牟田 <br/> 山梨学院　.　7三島＿　33.2　.　09　.　767.5　.　08(08)　8上田　⇔　天竜 <br/> 鳥取大学　.　7米子＿　33.2　.　09　.　766.2　.　09(09)　8玖珂 <br/> 日本大学　.　7練馬＿　31.1　.　16　.　763.4　.　10(10)　8府中 <br/> ---------------------------------------------------　 <br/> 三重大学　.　7津＿＿　31.3　.　15　.　762.4　.　11(11)　8和歌山 <br/> 熊本学園　.　7犬飼＿　34.6　.　03　.　758.2　.　12(12)　8三角　⇔　院内 <br/> 金沢大学　.　7敦賀＿　31.6　.　14　.　750.2　.　13(14)　8小松　 <br/> 福島大学　.　7寺泊＿　30.7　.　17　.　750.1　.　14(13)　8喜多方　⇔　小出 <br/> 鹿児島大　.　7鹿児島　34.7　.　02　.　745.3　.　15(16)　8さつま柏原 <br/> 東北大学　.　7秋田＿　30.3　.　18　.　745.1　.　16(15)　8東根 <br/> 四国大学　.　7新居浜　33.1　.　11　.　740.7　.　17(17)　8江川崎　↑明日から８区 <br/> 琉球大学　.　7那覇＿　32.4　.　13　.　709.5　.　18(18)　8西表島 <br/> <br/> ※速報のため修正の可能性があります <br/> ※(　)内は前日までの順位 <br/> ※選手名の前の数字は担当区　⇔は交代出走選手 <br/> 　７区735kmまで　８区841kmまで </span></div>"
  },
  {
    "timestamp": "2025-08-14T00:00:50",
    "posted_name": "■駅弁監督（season6）",
    "official_name": "駅弁監督（season6）",
    "tripcode": "◆rGlpXlZawQ",
    "content_html": "<div class=\"post-content\"> 福島大学 <br/> ７区４日目　寺泊　30.7km　４日間計109.4km <br/> 最終日に何とか真夏日が精一杯 <br/> 台風のアシストが無いと難しい選手とはっきり分かりました <br/> ４日間主な他選手では福島115.9と抜け、石川113.1、高田112.2、若松111.7（糸魚川112.5） <br/> 北東流のリスクも有り難区間でした <br/> 明後日には再び前線が南下してしまいそうです、残りメンバー小出も喜多方も耐える場面ですが今年の喜多方は一味違う、期待を加味して喜多方を走らせます <br/> <br/> 四国大学 <br/> ７区３日目　新居浜　33.1km <br/> 逆風絡みでしたが粘り、無事に襷渡しを終えました <br/> 次は調子を上げてきた江川崎が走るので、区間賞争いを期待して送り出します </div>"
  },
  {
    "timestamp": "2025-08-13T23:52:32",
    "posted_name": "■鳥取大学（白黒タビー監督）",
    "official_name": "鳥取大学（白黒タビー監督）",
    "tripcode": "◆CT6iZVF9L.",
    "content_html": "<div class=\"post-content\"> 鳥取大学７区　米子 <br/> ３日目　27.6km <br/> ４日目　33.2km <br/> <br/> ３日目は朝5時台の記録から積み上げられずも、４日目には前線が弱まったためか予想よりも走ってくれました <br/> ７区の米子及び補欠選手の記録を比べたところ、結果的にいずれの選手でも３日目での襷渡しは出来ない状況でしたが、４日間の合計では米子が最も少なくなってしまいました <br/> 襷渡しのタイミングが変わらなかったのも単なる偶然なので、やはり怒られてきます <br/> <br/> ８区は玖珂で変更なしです <br/> 天候にやや不安が残りますが、それ込みでも走ってくれると思います </div>"
  },
  {
    "timestamp": "2025-08-13T23:52:15",
    "posted_name": "■名古屋大学監督(ロマン派)",
    "official_name": "名古屋大学監督（ロマン派)",
    "tripcode": "◆Ai4OO8X72O3b",
    "content_html": "<div class=\"post-content\"> 名古屋大学　８区１日目　大府　34.4km　合計34.4km <br/> <br/> 予想の北西風が吹く青空とは真逆の、無風で日照ゼロの学内全域 <br/> 午前中は徒歩状態だった大府君、南からの晴れ間をもらって13時台に <br/> 34.3km、さらに遅い時間に0.1kmひねり出しました、危なかったです <br/> <br/> 今日までは岐阜勢が元気なく愛知勢で正解ですが明日からは苦手な南東風 <br/> 前半で岐阜勢を並べ倒して防戦した海からの南東風ですが、よりによって <br/> 正選手では最も海風に弱い大府君に当たってしまいます <br/> 午後はダメでしょう、午前中に何とかのばして食い下ってくれ <br/> <br/> 広島経済大学　８区　１日目　引田　33.4km　合計33.4km <br/> <br/> 昨日の悪い予感が当たり、北東風海風変換状態になり日照満点で <br/> 正午29℃台の避暑地化していた引田君、午後からは日照も無くなり <br/> 終わったかと思われましたが、夕方になり岡山の応援部員の奈義君の <br/> 声がとどいたのか、凪の時間に日照が出て小ダッシュしました <br/> <br/> 他の香川勢は明日も問題ないですが引田君は端っこ沿岸なので心配です </div>"
  },
  {
    "timestamp": "2025-08-13T23:44:31",
    "posted_name": "■全日本学連選抜監督(夏の日の1994)",
    "official_name": "全日本学連選抜監督（夏の日の1994)",
    "tripcode": "◆oIdAWXadP6",
    "content_html": "<div class=\"post-content\"> 学連選抜 <br/> ８区１日目　飯塚選手　34.6km <br/> <br/> 大本営発表には届きませんが概ね想定通り <br/> 前半の九州2枚は失敗でしたが、後半2枚は上手くいってくれそうです <br/> 明日も大本営は割と強気ですが、下層気温が少し上がる代わりに北風に変わるのが早そうで微妙なところです <br/> <br/> 鹿児島大学 <br/> ７区３日目　鹿児島選手　34.7km <br/> <br/> 今日は日照も多く、昨日の鬱憤を晴らす走りでした <br/> 残念ながら学内1位は叶いませんでしたが、もしかしたら区間賞を狙えるかも…… <br/> <br/> ８区はさつま柏原君ですが、序盤に使わなかったことを後悔していたので、少しでも遅れた分を取り返してほしいです </div>"
  },
  {
    "timestamp": "2025-08-13T22:59:08",
    "posted_name": "■駅弁監督（season6）",
    "official_name": "駅弁監督（season6）",
    "tripcode": "◆rGlpXlZawQ",
    "content_html": "<div class=\"post-content\"> 【選手交代】 <br/> 大学名: 福島大学 <br/> 区間: ８区 <br/> 交代: 小出 → 喜多方 </div>"
  },
  {
    "timestamp": "2025-08-13T21:21:00",
    "posted_name": "■山梨学院大学監督【大子さん大誤算】",
    "official_name": "山梨学院大学監督【大子さん大誤算】",
    "tripcode": "◆y9HH0rjqmw",
    "content_html": "<div class=\"post-content\"> 山学大 <br/> 8区 天竜→上田 </div>"
  },
  {
    "timestamp": "2025-08-13T20:55:51",
    "posted_name": "■熊本学園大学（風来の試練）",
    "official_name": "熊本学園大学（風来の試練）",
    "tripcode": "◆g8a8AxWMVk",
    "content_html": "<div class=\"post-content\"> 三重大ですが、シード線上ということもあり、まだ勝負どころではないと判断し、和歌山君のママでいきたいと思います <br/> また寝る前に気持ちが揺らぐかもしれませんが </div>"
  }
]