[
  {
    "rank": 1,
    "team_name": "名古屋大学",
    "team_short_name": "名大",
    "runner_name": "大府",
    "total_distance_km": 790.9,
    "latitude": 34.39219580631005,
    "longitude": 133.14367892533383
  },
  {
    "rank": 2,
    "team_name": "上武大学",
    "team_short_name": "上武",
    "runner_name": "前橋",
    "total_distance_km": 781.6,
    "latitude": 34.416718394846896,
    "longitude": 133.2313799483101
  },
  {
    "rank": 3,
    "team_name": "関西大学",
    "team_short_name": "関大",
    "runner_name": "郡家",
    "total_distance_km": 780.6,
    "latitude": 34.424829216027874,
    "longitude": 133.22752763723693
  },
  {
    "rank": 4,
    "team_name": "学連選抜",
    "team_short_name": "学連",
    "runner_name": "飯塚",
    "total_distance_km": 768.2,
    "latitude": 34.48484216936938,
    "longitude": 133.3309845118966
  },
  {
    "rank": 5,
    "team_name": "広島経済大学",
    "team_short_name": "広経",
    "runner_name": "引田",
    "total_distance_km": 767.8,
    "latitude": 34.48545240119742,
    "longitude": 133.33519486916686
  },
  {
    "rank": 6,
    "team_name": "立命館大学",
    "team_short_name": "立命",
    "runner_name": "京都",
    "total_distance_km": 767.6,
    "latitude": 34.48477396032075,
    "longitude": 133.33721214015492
  },
  {
    "rank": 7,
    "team_name": "福岡大学",
    "team_short_name": "福岡",
    "runner_name": "口之津",
    "total_distance_km": 766.3,
    "latitude": 34.48567257099371,
    "longitude": 133.35035702726847
  },
  {
    "rank": 8,
    "team_name": "山梨学院大学",
    "team_short_name": "山学",
    "runner_name": "三島",
    "total_distance_km": 765.8,
    "latitude": 34.48556724357483,
    "longitude": 133.35576477120287
  },
  {
    "rank": 9,
    "team_name": "鳥取大学",
    "team_short_name": "鳥取",
    "runner_name": "米子",
    "total_distance_km": 764.8,
    "latitude": 34.485862129701175,
    "longitude": 133.36642717988917
  },
  {
    "rank": 10,
    "team_name": "日本大学",
    "team_short_name": "日大",
    "runner_name": "練馬",
    "total_distance_km": 762.6,
    "latitude": 34.48822979438929,
    "longitude": 133.3899824985935
  },
  {
    "rank": 11,
    "team_name": "三重大学",
    "team_short_name": "三重",
    "runner_name": "津",
    "total_distance_km": 760.6,
    "latitude": 34.494176611037524,
    "longitude": 133.41024027975357
  },
  {
    "rank": 12,
    "team_name": "熊本学園大学",
    "team_short_name": "熊学",
    "runner_name": "犬飼",
    "total_distance_km": 753.7,
    "latitude": 34.50802918534444,
    "longitude": 133.47648075457482
  },
  {
    "rank": 13,
    "team_name": "福島大学",
    "team_short_name": "福島",
    "runner_name": "寺泊",
    "total_distance_km": 748.0,
    "latitude": 34.49932403184722,
    "longitude": 133.53200783666935
  },
  {
    "rank": 14,
    "team_name": "金沢大学",
    "team_short_name": "金沢",
    "runner_name": "敦賀",
    "total_distance_km": 747.5,
    "latitude": 34.50005399224781,
    "longitude": 133.53738018569507
  },
  {
    "rank": 15,
    "team_name": "東北大学",
    "team_short_name": "東北",
    "runner_name": "秋田",
    "total_distance_km": 743.4,
    "latitude": 34.51992814607728,
    "longitude": 133.57400131886803
  },
  {
    "rank": 16,
    "team_name": "鹿児島大学",
    "team_short_name": "鹿大",
    "runner_name": "鹿児島",
    "total_distance_km": 741.6,
    "latitude": 34.52793538837617,
    "longitude": 133.59103080306744
  },
  {
    "rank": 17,
    "team_name": "四国大学",
    "team_short_name": "四国",
    "runner_name": "新居浜",
    "total_distance_km": 738.9,
    "latitude": 34.53614819592263,
    "longitude": 133.6179889540667
  },
  {
    "rank": 18,
    "team_name": "琉球大学",
    "team_short_name": "琉球",
    "runner_name": "那覇",
    "total_distance_km": 708.6,
    "latitude": 34.65281326974405,
    "longitude": 133.8965538011874
  }
]