[
  {
    "rank": 1,
    "team_name": "名古屋大学",
    "team_short_name": "名大",
    "runner_name": "多治見",
    "total_distance_km": 448.7,
    "latitude": 34.98516530368033,
    "longitude": 136.1189555104228
  },
  {
    "rank": 2,
    "team_name": "鳥取大学",
    "team_short_name": "鳥取",
    "runner_name": "境",
    "total_distance_km": 445.8,
    "latitude": 34.98183036229798,
    "longitude": 136.14966460764003
  },
  {
    "rank": 3,
    "team_name": "福島大学",
    "team_short_name": "福島",
    "runner_name": "福島",
    "total_distance_km": 445.4,
    "latitude": 34.98078745198562,
    "longitude": 136.1538580579717
  },
  {
    "rank": 4,
    "team_name": "上武大学",
    "team_short_name": "上武",
    "runner_name": "桐生",
    "total_distance_km": 442.3,
    "latitude": 34.967208285940266,
    "longitude": 136.182755932608
  },
  {
    "rank": 5,
    "team_name": "立命館大学",
    "team_short_name": "立命",
    "runner_name": "舞鶴",
    "total_distance_km": 442.2,
    "latitude": 34.96667719586188,
    "longitude": 136.1836406955762
  },
  {
    "rank": 6,
    "team_name": "広島経済大学",
    "team_short_name": "広経",
    "runner_name": "高梁",
    "total_distance_km": 441.9,
    "latitude": 34.965119393979606,
    "longitude": 136.18632572219406
  },
  {
    "rank": 7,
    "team_name": "福岡大学",
    "team_short_name": "福岡",
    "runner_name": "前原",
    "total_distance_km": 440.8,
    "latitude": 34.95915342673412,
    "longitude": 136.19593032238095
  },
  {
    "rank": 8,
    "team_name": "関西大学",
    "team_short_name": "関大",
    "runner_name": "枚方",
    "total_distance_km": 439.5,
    "latitude": 34.95728788140201,
    "longitude": 136.20959823882114
  },
  {
    "rank": 9,
    "team_name": "東北大学",
    "team_short_name": "東北",
    "runner_name": "一関",
    "total_distance_km": 437.8,
    "latitude": 34.95191082707257,
    "longitude": 136.22695478873462
  },
  {
    "rank": 10,
    "team_name": "熊本学園大学",
    "team_short_name": "熊学",
    "runner_name": "熊本",
    "total_distance_km": 435.2,
    "latitude": 34.94082180527895,
    "longitude": 136.25165455573816
  },
  {
    "rank": 11,
    "team_name": "学連選抜",
    "team_short_name": "学連",
    "runner_name": "上",
    "total_distance_km": 433.2,
    "latitude": 34.93829270071331,
    "longitude": 136.27302930662898
  },
  {
    "rank": 12,
    "team_name": "日本大学",
    "team_short_name": "日大",
    "runner_name": "牛久",
    "total_distance_km": 432.6,
    "latitude": 34.93763887116785,
    "longitude": 136.27937451389704
  },
  {
    "rank": 13,
    "team_name": "金沢大学",
    "team_short_name": "金沢",
    "runner_name": "志賀",
    "total_distance_km": 427.1,
    "latitude": 34.9088219769592,
    "longitude": 136.32611865463764
  },
  {
    "rank": 14,
    "team_name": "山梨学院大学",
    "team_short_name": "山学",
    "runner_name": "浜松",
    "total_distance_km": 426.8,
    "latitude": 34.907890333142674,
    "longitude": 136.32920022085926
  },
  {
    "rank": 15,
    "team_name": "三重大学",
    "team_short_name": "三重",
    "runner_name": "風屋",
    "total_distance_km": 425.9,
    "latitude": 34.90168634256611,
    "longitude": 136.3349277289995
  },
  {
    "rank": 16,
    "team_name": "四国大学",
    "team_short_name": "四国",
    "runner_name": "松山",
    "total_distance_km": 415.5,
    "latitude": 34.851080082033036,
    "longitude": 136.4029761901956
  },
  {
    "rank": 17,
    "team_name": "鹿児島大学",
    "team_short_name": "鹿大",
    "runner_name": "西米良",
    "total_distance_km": 404.0,
    "latitude": 34.87712713820143,
    "longitude": 136.50775554160788
  },
  {
    "rank": 18,
    "team_name": "琉球大学",
    "team_short_name": "琉球",
    "runner_name": "名護",
    "total_distance_km": 380.6,
    "latitude": 35.01985733991753,
    "longitude": 136.6672851330488
  }
]