[
  {
    "rank": 1,
    "team_name": "立命館大学",
    "runner_name": "京田辺",
    "total_distance_km": 295.1,
    "latitude": 34.809259345446534,
    "longitude": 137.35699374915248
  },
  {
    "rank": 2,
    "team_name": "福島大学",
    "runner_name": "津川",
    "total_distance_km": 292.9,
    "latitude": 34.793169594781126,
    "longitude": 137.37103472827965
  },
  {
    "rank": 3,
    "team_name": "上武大学",
    "runner_name": "熊谷",
    "total_distance_km": 289.8,
    "latitude": 34.77074198904368,
    "longitude": 137.3905570431921
  },
  {
    "rank": 4,
    "team_name": "名古屋大学",
    "runner_name": "大垣",
    "total_distance_km": 289.3,
    "latitude": 34.76745259201439,
    "longitude": 137.3923091331144
  },
  {
    "rank": 4,
    "team_name": "日本大学",
    "runner_name": "下館",
    "total_distance_km": 289.3,
    "latitude": 34.76745259201439,
    "longitude": 137.3923091331144
  },
  {
    "rank": 6,
    "team_name": "東北大学",
    "runner_name": "高畠",
    "total_distance_km": 288.3,
    "latitude": 34.76438330756511,
    "longitude": 137.40241218729201
  },
  {
    "rank": 7,
    "team_name": "福岡大学",
    "runner_name": "黒木",
    "total_distance_km": 286.9,
    "latitude": 34.754166539882185,
    "longitude": 137.41131816108486
  },
  {
    "rank": 8,
    "team_name": "鳥取大学",
    "runner_name": "広瀬",
    "total_distance_km": 286.8,
    "latitude": 34.75333144093025,
    "longitude": 137.41172810881415
  },
  {
    "rank": 9,
    "team_name": "金沢大学",
    "runner_name": "七尾",
    "total_distance_km": 285.8,
    "latitude": 34.744769894097004,
    "longitude": 137.41489779143325
  },
  {
    "rank": 10,
    "team_name": "広島経済大学",
    "runner_name": "府中（広島）",
    "total_distance_km": 284.5,
    "latitude": 34.73631950052728,
    "longitude": 137.42425864881275
  },
  {
    "rank": 11,
    "team_name": "関西大学",
    "runner_name": "上郡",
    "total_distance_km": 283.4,
    "latitude": 34.72683758860322,
    "longitude": 137.42682000878054
  },
  {
    "rank": 12,
    "team_name": "学連選抜",
    "runner_name": "大村",
    "total_distance_km": 282.5,
    "latitude": 34.72364977877952,
    "longitude": 137.43567358399403
  },
  {
    "rank": 13,
    "team_name": "熊本学園大学",
    "runner_name": "八代",
    "total_distance_km": 282.2,
    "latitude": 34.72274001736955,
    "longitude": 137.43875743516585
  },
  {
    "rank": 14,
    "team_name": "山梨学院大学",
    "runner_name": "大月",
    "total_distance_km": 278.0,
    "latitude": 34.707403829878395,
    "longitude": 137.47786521588395
  },
  {
    "rank": 15,
    "team_name": "三重大学",
    "runner_name": "小俣",
    "total_distance_km": 274.7,
    "latitude": 34.68647213129826,
    "longitude": 137.49938307176149
  },
  {
    "rank": 16,
    "team_name": "四国大学",
    "runner_name": "御荘",
    "total_distance_km": 273.3,
    "latitude": 34.67994797886462,
    "longitude": 137.50803221042133
  },
  {
    "rank": 17,
    "team_name": "鹿児島大学",
    "runner_name": "加久藤",
    "total_distance_km": 255.8,
    "latitude": 34.68812834883322,
    "longitude": 137.69010509731132
  },
  {
    "rank": 18,
    "team_name": "琉球大学",
    "runner_name": "盛山",
    "total_distance_km": 245.9,
    "latitude": 34.72056686508638,
    "longitude": 137.7783557074646
  }
]