[
  {
    "rank": 1,
    "team_name": "名古屋大学",
    "team_short_name": "名大",
    "runner_name": "大府",
    "total_distance_km": 827.7,
    "latitude": 34.400273903296764,
    "longitude": 132.8013712783278
  },
  {
    "rank": 2,
    "team_name": "関西大学",
    "team_short_name": "関大",
    "runner_name": "郡家",
    "total_distance_km": 817.5,
    "latitude": 34.387868175709,
    "longitude": 132.89855518983254
  },
  {
    "rank": 3,
    "team_name": "上武大学",
    "team_short_name": "上武",
    "runner_name": "前橋",
    "total_distance_km": 815.0,
    "latitude": 34.39883821955609,
    "longitude": 132.9214458725446
  },
  {
    "rank": 4,
    "team_name": "学連選抜",
    "team_short_name": "学連",
    "runner_name": "飯塚",
    "total_distance_km": 806.5,
    "latitude": 34.40327539919247,
    "longitude": 132.9986595928221
  },
  {
    "rank": 5,
    "team_name": "立命館大学",
    "team_short_name": "立命",
    "runner_name": "京都",
    "total_distance_km": 805.3,
    "latitude": 34.40570155696255,
    "longitude": 133.0108644372747
  },
  {
    "rank": 6,
    "team_name": "広島経済大学",
    "team_short_name": "広経",
    "runner_name": "引田",
    "total_distance_km": 802.6,
    "latitude": 34.39440286537506,
    "longitude": 133.03599056403266
  },
  {
    "rank": 7,
    "team_name": "福岡大学",
    "team_short_name": "福岡",
    "runner_name": "大牟田",
    "total_distance_km": 801.7,
    "latitude": 34.393581329130484,
    "longitude": 133.04519513074098
  },
  {
    "rank": 8,
    "team_name": "山梨学院大学",
    "team_short_name": "山学",
    "runner_name": "上田",
    "total_distance_km": 800.8,
    "latitude": 34.39086709027336,
    "longitude": 133.05267709083404
  },
  {
    "rank": 9,
    "team_name": "鳥取大学",
    "team_short_name": "鳥取",
    "runner_name": "玖珂",
    "total_distance_km": 800.1,
    "latitude": 34.39013239187714,
    "longitude": 133.0594636816173
  },
  {
    "rank": 10,
    "team_name": "三重大学",
    "team_short_name": "三重",
    "runner_name": "和歌山",
    "total_distance_km": 796.0,
    "latitude": 34.39577852941909,
    "longitude": 133.09859896355727
  },
  {
    "rank": 11,
    "team_name": "日本大学",
    "team_short_name": "日大",
    "runner_name": "府中（東京）",
    "total_distance_km": 795.3,
    "latitude": 34.39268864090057,
    "longitude": 133.10498105549294
  },
  {
    "rank": 12,
    "team_name": "熊本学園大学",
    "team_short_name": "熊学",
    "runner_name": "三角",
    "total_distance_km": 791.8,
    "latitude": 34.38715698422016,
    "longitude": 133.13615021219192
  },
  {
    "rank": 13,
    "team_name": "金沢大学",
    "team_short_name": "金沢",
    "runner_name": "小松",
    "total_distance_km": 783.4,
    "latitude": 34.41022117204239,
    "longitude": 133.21726096688494
  },
  {
    "rank": 14,
    "team_name": "福島大学",
    "team_short_name": "福島",
    "runner_name": "喜多方",
    "total_distance_km": 782.1,
    "latitude": 34.41279963321009,
    "longitude": 133.22994065443655
  },
  {
    "rank": 15,
    "team_name": "鹿児島大学",
    "team_short_name": "鹿大",
    "runner_name": "さつま柏原",
    "total_distance_km": 780.3,
    "latitude": 34.42748251782233,
    "longitude": 133.2280298468194
  },
  {
    "rank": 16,
    "team_name": "四国大学",
    "team_short_name": "四国",
    "runner_name": "江川崎",
    "total_distance_km": 776.6,
    "latitude": 34.450387705853174,
    "longitude": 133.25236781904266
  },
  {
    "rank": 16,
    "team_name": "東北大学",
    "team_short_name": "東北",
    "runner_name": "東根",
    "total_distance_km": 776.6,
    "latitude": 34.450387705853174,
    "longitude": 133.25236781904266
  },
  {
    "rank": 18,
    "team_name": "琉球大学",
    "team_short_name": "琉球",
    "runner_name": "那覇",
    "total_distance_km": 741.4,
    "latitude": 34.52874017895525,
    "longitude": 133.59298016599405
  }
]