{
  "lastUpdated": "2025-12-27T20:05:02.880950",
  "snapshots": [
    {
      "filename": "realtime_report_20251227_0005.json",
      "timestamp": "2025-12-27T00:05:00",
      "timestamp_str": "20251227_0005"
    },
    {
      "filename": "realtime_report_20251227_0105.json",
      "timestamp": "2025-12-27T01:05:00",
      "timestamp_str": "20251227_0105"
    },
    {
      "filename": "realtime_report_20251227_0205.json",
      "timestamp": "2025-12-27T02:05:00",
      "timestamp_str": "20251227_0205"
    },
    {
      "filename": "realtime_report_20251227_0305.json",
      "timestamp": "2025-12-27T03:05:00",
      "timestamp_str": "20251227_0305"
    },
    {
      "filename": "realtime_report_20251227_0405.json",
      "timestamp": "2025-12-27T04:05:00",
      "timestamp_str": "20251227_0405"
    },
    {
      "filename": "realtime_report_20251227_0505.json",
      "timestamp": "2025-12-27T05:05:00",
      "timestamp_str": "20251227_0505"
    },
    {
      "filename": "realtime_report_20251227_0605.json",
      "timestamp": "2025-12-27T06:05:00",
      "timestamp_str": "20251227_0605"
    },
    {
      "filename": "realtime_report_20251227_0705.json",
      "timestamp": "2025-12-27T07:05:00",
      "timestamp_str": "20251227_0705"
    },
    {
      "filename": "realtime_report_20251227_0805.json",
      "timestamp": "2025-12-27T08:05:00",
      "timestamp_str": "20251227_0805"
    },
    {
      "filename": "realtime_report_20251227_0905.json",
      "timestamp": "2025-12-27T09:05:00",
      "timestamp_str": "20251227_0905"
    },
    {
      "filename": "realtime_report_20251227_1005.json",
      "timestamp": "2025-12-27T10:05:00",
      "timestamp_str": "20251227_1005"
    },
    {
      "filename": "realtime_report_20251227_1105.json",
      "timestamp": "2025-12-27T11:05:00",
      "timestamp_str": "20251227_1105"
    },
    {
      "filename": "realtime_report_20251227_1205.json",
      "timestamp": "2025-12-27T12:05:00",
      "timestamp_str": "20251227_1205"
    },
    {
      "filename": "realtime_report_20251227_1305.json",
      "timestamp": "2025-12-27T13:05:00",
      "timestamp_str": "20251227_1305"
    },
    {
      "filename": "realtime_report_20251227_1405.json",
      "timestamp": "2025-12-27T14:05:00",
      "timestamp_str": "20251227_1405"
    },
    {
      "filename": "realtime_report_20251227_1505.json",
      "timestamp": "2025-12-27T15:05:00",
      "timestamp_str": "20251227_1505"
    },
    {
      "filename": "realtime_report_20251227_1605.json",
      "timestamp": "2025-12-27T16:05:00",
      "timestamp_str": "20251227_1605"
    },
    {
      "filename": "realtime_report_20251227_1705.json",
      "timestamp": "2025-12-27T17:05:00",
      "timestamp_str": "20251227_1705"
    },
    {
      "filename": "realtime_report_20251227_1805.json",
      "timestamp": "2025-12-27T18:05:00",
      "timestamp_str": "20251227_1805"
    },
    {
      "filename": "realtime_report_20251227_1905.json",
      "timestamp": "2025-12-27T19:05:00",
      "timestamp_str": "20251227_1905"
    },
    {
      "filename": "realtime_report_20251227_2005.json",
      "timestamp": "2025-12-27T20:05:00",
      "timestamp_str": "20251227_2005"
    }
  ]
}