{
  "lastUpdated": "2026-01-09T07:05:02.018902",
  "snapshots": [
    {
      "filename": "realtime_report_20260109_0005.json",
      "timestamp": "2026-01-09T00:05:00",
      "timestamp_str": "20260109_0005"
    },
    {
      "filename": "realtime_report_20260109_0105.json",
      "timestamp": "2026-01-09T01:05:00",
      "timestamp_str": "20260109_0105"
    },
    {
      "filename": "realtime_report_20260109_0205.json",
      "timestamp": "2026-01-09T02:05:00",
      "timestamp_str": "20260109_0205"
    },
    {
      "filename": "realtime_report_20260109_0305.json",
      "timestamp": "2026-01-09T03:05:00",
      "timestamp_str": "20260109_0305"
    },
    {
      "filename": "realtime_report_20260109_0405.json",
      "timestamp": "2026-01-09T04:05:00",
      "timestamp_str": "20260109_0405"
    },
    {
      "filename": "realtime_report_20260109_0505.json",
      "timestamp": "2026-01-09T05:05:00",
      "timestamp_str": "20260109_0505"
    },
    {
      "filename": "realtime_report_20260109_0605.json",
      "timestamp": "2026-01-09T06:05:00",
      "timestamp_str": "20260109_0605"
    },
    {
      "filename": "realtime_report_20260109_0705.json",
      "timestamp": "2026-01-09T07:05:00",
      "timestamp_str": "20260109_0705"
    }
  ]
}